setup.cfg
setup.py
hackercodecs/__init__.py
hackercodecs.egg-info/PKG-INFO
hackercodecs.egg-info/SOURCES.txt
hackercodecs.egg-info/dependency_links.txt
hackercodecs.egg-info/top_level.txt