Metadata-Version: 1.0
Name: hackercodecs
Version: 0.3
Summary: A set of codecs for hackers
Home-page: https://github.com/jdukes/hackercodecs
Author: Josh Dukes
Author-email: hex@neg9.org
License: MIT
Keywords: hacker,codecs,CTF
Platform: UNKNOWN
